mlend_probability/Binomialdistribution.py
mlend_probability/Gaussiandistribution.py
mlend_probability/Generaldistribution.py
mlend_probability/__init__.py
mlend_probability-0.1.dist-info/DESCRIPTION.rst
mlend_probability-0.1.dist-info/METADATA
mlend_probability-0.1.dist-info/RECORD
mlend_probability-0.1.dist-info/WHEEL
mlend_probability-0.1.dist-info/metadata.json
mlend_probability-0.1.dist-info/top_level.txt
