Metadata-Version: 2.0
Name: mlend-probability
Version: 0.1
Summary: Gaussian and Binomial distribution
Home-page: UNKNOWN
Author: Foxan Ng
Author-email: foxan.ng@gmail.com
License: UNKNOWN
Platform: UNKNOWN
Classifier: Programming Language :: Python :: 3
Classifier: License :: OSI Approved :: MIT License
Classifier: Operating System :: OS Independent
Requires-Dist: matplotlib (>=3.0.3)
